envon/__init__.py
envon/__main__.py
envon/bootstrap_bash.sh
envon/bootstrap_csh.csh
envon/bootstrap_csh_fixed.csh
envon/bootstrap_fish.fish
envon/bootstrap_nushell.nu
envon/bootstrap_powershell.ps1
envon/bootstrap_sh.sh
envon/envon.py
envon-0.1.4.dist-info/METADATA
envon-0.1.4.dist-info/WHEEL
envon-0.1.4.dist-info/entry_points.txt
envon-0.1.4.dist-info/licenses/LICENSE
envon-0.1.4.dist-info/RECORD
