Metadata-Version: 2.4
Name: envon
Version: 0.1.4
Summary: Emit the activation command for the nearest Python virtual environment and install shell bootstrap wrappers.
Project-URL: Homepage, https://github.com/userfrom1995/envon
Project-URL: Repository, https://github.com/userfrom1995/envon
Author-email: User1995 <userfrom1995@gmail.com>
License: MIT License
License-File: LICENSE
Keywords: activation,bootstrap,shell,venv,virtualenv
Classifier: Environment :: Console
Classifier: License :: OSI Approved :: MIT License
Classifier: Operating System :: OS Independent
Classifier: Programming Language :: Python :: 3
Classifier: Programming Language :: Python :: 3 :: Only
Classifier: Topic :: Software Development :: Build Tools
Classifier: Topic :: System :: Shells
Requires-Python: >=3.8
Requires-Dist: virtualenv>=20
